flet_lottie/__init__.py
flet_lottie/lottie.py
flet_lottie-0.80.5.dist-info/licenses/LICENSE
flutter/flet_lottie/analysis_options.yaml
flutter/flet_lottie/pubspec.lock
flutter/flet_lottie/pubspec.yaml
flutter/flet_lottie/lib/flet_lottie.dart
flutter/flet_lottie/lib/src/extension.dart
flutter/flet_lottie/lib/src/lottie.dart
flet_lottie-0.80.5.dist-info/METADATA
flet_lottie-0.80.5.dist-info/WHEEL
flet_lottie-0.80.5.dist-info/top_level.txt
flet_lottie-0.80.5.dist-info/RECORD
